robottest/__init__.py
robottest/abc.py
robottest/ceshi.py
robottest-0.1.4.dist-info/METADATA
robottest-0.1.4.dist-info/WHEEL
robottest-0.1.4.dist-info/RECORD
