Metadata-Version: 2.1
Name: robottest
Version: 0.1.4
Summary: 
Author: yinhejianke
Author-email: yinhejianke@yinehajianke.com
Requires-Python: >=3.10,<4.0
Classifier: Programming Language :: Python :: 3
Classifier: Programming Language :: Python :: 3.10
Classifier: Programming Language :: Python :: 3.11
Classifier: Programming Language :: Python :: 3.12
Requires-Dist: django (>=5.1.2,<6.0.0)
Requires-Dist: python-gitlab (>=4.13.0,<5.0.0)
Requires-Dist: robotframework (>=7.1,<8.0)
